{ "products" : [
        {
            "title": "First Item",
            "price": "3299",
            "id":"1",
            "loc": "Japan"
        },
        {
            "title": "Second Item",
            "price": "3299",
            "id":"2",
            "loc": "China"
        },
        {
            "title": "Third Item",
            "price": "3299",
            "id":"3",
            "loc": "USA"
        },
        {
            "title": "Fourth Item",
            "price": "3299",
            "id":"4",
            "loc": "Japan"
        }
    ],
 "carousel" : [
        {
            "title": "FirstItem",
            "price": "3299",
            "id":"1",
            "techs": "Japan"            
        },
        {
            "title": "SecondItem",
            "price": 329,
            "id":2,
            "techs": "China"            
        },
        {
            "title": "ThirdItem",
            "price": "3299",
            "id":"3",
            "techs": "USA"           
        },
        {
            "title": "FourthItem",
            "price": "3299",
            "id":"4",
            "techs": "Japan"
        }
    ]
}